itl_service/__init__.py
itl_service/devices.py
ITL_service-1.3.dist-info/METADATA
ITL_service-1.3.dist-info/WHEEL
ITL_service-1.3.dist-info/top_level.txt
ITL_service-1.3.dist-info/RECORD
