Metadata-Version: 2.1
Name: ITL_service
Version: 1.3
Summary: Libreria para control de dispositivo ITL NV4000 y SCS
Home-page: https://github.com/Santiago702/itl_service
Author: Santiago Cuervo
Author-email: santic9999@gmail.com
Classifier: Programming Language :: Python :: 3
Classifier: License :: OSI Approved :: MIT License
Classifier: Operating System :: OS Independent
Requires-Python: >=3.6
Requires-Dist: requests
